tg_signer/__init__.py
tg_signer/__main__.py
tg_signer/ai_tools.py
tg_signer/config.py
tg_signer/core.py
tg_signer/logger.py
tg_signer/utils.py
tg_signer/cli/__init__.py
tg_signer/cli/monitor.py
tg_signer/cli/signer.py
tg_signer/notification/__init__.py
tg_signer/notification/server_chan.py
tg_signer/webui/__init__.py
tg_signer/webui/__main__.py
tg_signer/webui/app.py
tg_signer/webui/data.py
tg_signer/webui/interactive.py
tg_signer/webui/schema_utils.py
tg_signer-0.8.4.dist-info/licenses/LICENSE
tg_signer-0.8.4.dist-info/METADATA
tg_signer-0.8.4.dist-info/WHEEL
tg_signer-0.8.4.dist-info/entry_points.txt
tg_signer-0.8.4.dist-info/top_level.txt
tg_signer-0.8.4.dist-info/RECORD
