Metadata-Version: 2.4
Name: tg-signer
Version: 0.8.4
Summary: Automated Telegram tasks (check-ins, sending messages, keyboard clicks, AI replies, etc.); monitoring, forwarding, and auto-replying to private, group, and channel messages.
Author-email: Amchii <finethankuandyou@gmail.com>
License-Expression: BSD-3-Clause
Project-URL: Homepage, https://github.com/amchii/tg-signer
Project-URL: Repository, https://github.com/amchii/tg-signer
Classifier: Intended Audience :: Developers
Classifier: Programming Language :: Python :: 3 :: Only
Requires-Python: >=3.10
License-File: LICENSE
Requires-Dist: kurigram<=2.2.7
Requires-Dist: click
Requires-Dist: pydantic
Requires-Dist: openai
Requires-Dist: croniter
Requires-Dist: json_repair
Requires-Dist: typing-extensions
Requires-Dist: httpx
Provides-Extra: speedup
Requires-Dist: tgcrypto; extra == "speedup"
Provides-Extra: gui
Requires-Dist: nicegui; extra == "gui"
Dynamic: license-file
